{
  "type": "pull",
  "pull": {
    "url": "https://api.github.com/repos/bitcoin/bitcoin/pulls/26573",
    "id": 1135903867,
    "node_id": "PR_kwDOABII585DtIR7",
    "html_url": "https://github.com/bitcoin/bitcoin/pull/26573",
    "diff_url": "https://github.com/bitcoin/bitcoin/pull/26573.diff",
    "patch_url": "https://github.com/bitcoin/bitcoin/pull/26573.patch",
    "issue_url": "https://api.github.com/repos/bitcoin/bitcoin/issues/26573",
    "commits_url": "https://api.github.com/repos/bitcoin/bitcoin/pulls/26573/commits",
    "review_comments_url": "https://api.github.com/repos/bitcoin/bitcoin/pulls/26573/comments",
    "review_comment_url": "https://api.github.com/repos/bitcoin/bitcoin/pulls/comments%7B/number%7D",
    "comments_url": "https://api.github.com/repos/bitcoin/bitcoin/issues/26573/comments",
    "statuses_url": "https://api.github.com/repos/bitcoin/bitcoin/statuses/08f288fddc33f6ff3cf89ef4960594c0a28df2f5",
    "number": 26573,
    "state": "open",
    "locked": false,
    "maintainer_can_modify": true,
    "title": "Wallet: don't underestimate the fees when spending a Taproot output",
    "user": {
      "login": "darosior",
      "id": 22457751,
      "node_id": "MDQ6VXNlcjIyNDU3NzUx",
      "avatar_url": "https://avatars.githubusercontent.com/u/22457751?v=4",
      "gravatar_id": "",
      "url": "https://api.github.com/users/darosior",
      "html_url": "https://github.com/darosior",
      "followers_url": "https://api.github.com/users/darosior/followers",
      "following_url": "https://api.github.com/users/darosior/following%7B/other_user%7D",
      "gists_url": "https://api.github.com/users/darosior/gists%7B/gist_id%7D",
      "starred_url": "https://api.github.com/users/darosior/starred%7B/owner%7D%7B/repo%7D",
      "subscriptions_url": "https://api.github.com/users/darosior/subscriptions",
      "organizations_url": "https://api.github.com/users/darosior/orgs",
      "repos_url": "https://api.github.com/users/darosior/repos",
      "events_url": "https://api.github.com/users/darosior/events%7B/privacy%7D",
      "received_events_url": "https://api.github.com/users/darosior/received_events",
      "type": "User",
      "site_admin": false
    },
    "body": "Based on #26567. Alternative to #23502.\r\n\r\nCurrently, when estimating the size an input spending a Taproot output sill have once signed, we always assume the key path will be used. Even if there are script paths. This can lead to pretty severe fee underestimation if the script path turns out to be used in the end. So instead assume the most expensive between all script paths and the key path will be used.\r\n\r\nThis is still not ideal, as there may be a huge gap between the size of a script path spend and a key path spend. Still, this is less bad than undershooting the fees.",
    "labels": [
      {
        "id": 149424,
        "node_id": "MDU6TGFiZWwxNDk0MjQ=",
        "url": "https://api.github.com/repos/bitcoin/bitcoin/labels/Wallet",
        "name": "Wallet",
        "color": "08a781",
        "default": false
      },
      {
        "id": 955867938,
        "node_id": "MDU6TGFiZWw5NTU4Njc5Mzg=",
        "url": "https://api.github.com/repos/bitcoin/bitcoin/labels/Needs%20rebase",
        "name": "Needs rebase",
        "description": "",
        "color": "cccccc",
        "default": false
      }
    ],
    "created_at": "2022-11-25T12:21:59Z",
    "updated_at": "2023-05-25T01:21:58Z",
    "mergeable": false,
    "mergeable_state": "dirty",
    "merge_commit_sha": "2538b0fc0a34eaccffa43a6485ace550ce878f5e",
    "assignees": [],
    "requested_reviewers": [],
    "requested_teams": [],
    "rebaseable": false,
    "head": {
      "label": "darosior:taproot_over_dont_under_estimate",
      "ref": "taproot_over_dont_under_estimate",
      "sha": "08f288fddc33f6ff3cf89ef4960594c0a28df2f5",
      "user": {
        "login": "darosior",
        "id": 22457751,
        "node_id": "MDQ6VXNlcjIyNDU3NzUx",
        "avatar_url": "https://avatars.githubusercontent.com/u/22457751?v=4",
        "gravatar_id": "",
        "url": "https://api.github.com/users/darosior",
        "html_url": "https://github.com/darosior",
        "followers_url": "https://api.github.com/users/darosior/followers",
        "following_url": "https://api.github.com/users/darosior/following%7B/other_user%7D",
        "gists_url": "https://api.github.com/users/darosior/gists%7B/gist_id%7D",
        "starred_url": "https://api.github.com/users/darosior/starred%7B/owner%7D%7B/repo%7D",
        "subscriptions_url": "https://api.github.com/users/darosior/subscriptions",
        "organizations_url": "https://api.github.com/users/darosior/orgs",
        "repos_url": "https://api.github.com/users/darosior/repos",
        "events_url": "https://api.github.com/users/darosior/events%7B/privacy%7D",
        "received_events_url": "https://api.github.com/users/darosior/received_events",
        "type": "User",
        "site_admin": false
      },
      "repo": {
        "id": 168868367,
        "node_id": "MDEwOlJlcG9zaXRvcnkxNjg4NjgzNjc=",
        "name": "bitcoin",
        "full_name": "darosior/bitcoin",
        "owner": {
          "login": "darosior",
          "id": 22457751,
          "node_id": "MDQ6VXNlcjIyNDU3NzUx",
          "avatar_url": "https://avatars.githubusercontent.com/u/22457751?v=4",
          "gravatar_id": "",
          "url": "https://api.github.com/users/darosior",
          "html_url": "https://github.com/darosior",
          "followers_url": "https://api.github.com/users/darosior/followers",
          "following_url": "https://api.github.com/users/darosior/following%7B/other_user%7D",
          "gists_url": "https://api.github.com/users/darosior/gists%7B/gist_id%7D",
          "starred_url": "https://api.github.com/users/darosior/starred%7B/owner%7D%7B/repo%7D",
          "subscriptions_url": "https://api.github.com/users/darosior/subscriptions",
          "organizations_url": "https://api.github.com/users/darosior/orgs",
          "repos_url": "https://api.github.com/users/darosior/repos",
          "events_url": "https://api.github.com/users/darosior/events%7B/privacy%7D",
          "received_events_url": "https://api.github.com/users/darosior/received_events",
          "type": "User",
          "site_admin": false
        },
        "private": false,
        "html_url": "https://github.com/darosior/bitcoin",
        "description": "Bitcoin Core integration/staging tree",
        "fork": true,
        "url": "https://api.github.com/repos/darosior/bitcoin",
        "archive_url": "https://api.github.com/repos/darosior/bitcoin/%7Barchive_format%7D%7B/ref%7D",
        "assignees_url": "https://api.github.com/repos/darosior/bitcoin/assignees%7B/user%7D",
        "blobs_url": "https://api.github.com/repos/darosior/bitcoin/git/blobs%7B/sha%7D",
        "branches_url": "https://api.github.com/repos/darosior/bitcoin/branches%7B/branch%7D",
        "collaborators_url": "https://api.github.com/repos/darosior/bitcoin/collaborators%7B/collaborator%7D",
        "comments_url": "https://api.github.com/repos/darosior/bitcoin/comments%7B/number%7D",
        "commits_url": "https://api.github.com/repos/darosior/bitcoin/commits%7B/sha%7D",
        "compare_url": "https://api.github.com/repos/darosior/bitcoin/compare/%7Bbase%7D...%7Bhead%7D",
        "contents_url": "https://api.github.com/repos/darosior/bitcoin/contents/%7B+path%7D",
        "contributors_url": "https://api.github.com/repos/darosior/bitcoin/contributors",
        "deployments_url": "https://api.github.com/repos/darosior/bitcoin/deployments",
        "downloads_url": "https://api.github.com/repos/darosior/bitcoin/downloads",
        "events_url": "https://api.github.com/repos/darosior/bitcoin/events",
        "forks_url": "https://api.github.com/repos/darosior/bitcoin/forks",
        "git_commits_url": "https://api.github.com/repos/darosior/bitcoin/git/commits%7B/sha%7D",
        "git_refs_url": "https://api.github.com/repos/darosior/bitcoin/git/refs%7B/sha%7D",
        "git_tags_url": "https://api.github.com/repos/darosior/bitcoin/git/tags%7B/sha%7D",
        "git_url": "git://github.com/darosior/bitcoin.git",
        "issue_comment_url": "https://api.github.com/repos/darosior/bitcoin/issues/comments%7B/number%7D",
        "issue_events_url": "https://api.github.com/repos/darosior/bitcoin/issues/events%7B/number%7D",
        "issues_url": "https://api.github.com/repos/darosior/bitcoin/issues%7B/number%7D",
        "keys_url": "https://api.github.com/repos/darosior/bitcoin/keys%7B/key_id%7D",
        "labels_url": "https://api.github.com/repos/darosior/bitcoin/labels%7B/name%7D",
        "languages_url": "https://api.github.com/repos/darosior/bitcoin/languages",
        "merges_url": "https://api.github.com/repos/darosior/bitcoin/merges",
        "milestones_url": "https://api.github.com/repos/darosior/bitcoin/milestones%7B/number%7D",
        "notifications_url": "https://api.github.com/repos/darosior/bitcoin/notifications%7B?since,all,participating}",
        "pulls_url": "https://api.github.com/repos/darosior/bitcoin/pulls%7B/number%7D",
        "releases_url": "https://api.github.com/repos/darosior/bitcoin/releases%7B/id%7D",
        "ssh_url": "git@github.com:darosior/bitcoin.git",
        "stargazers_url": "https://api.github.com/repos/darosior/bitcoin/stargazers",
        "statuses_url": "https://api.github.com/repos/darosior/bitcoin/statuses/%7Bsha%7D",
        "subscribers_url": "https://api.github.com/repos/darosior/bitcoin/subscribers",
        "subscription_url": "https://api.github.com/repos/darosior/bitcoin/subscription",
        "tags_url": "https://api.github.com/repos/darosior/bitcoin/tags",
        "teams_url": "https://api.github.com/repos/darosior/bitcoin/teams",
        "trees_url": "https://api.github.com/repos/darosior/bitcoin/git/trees%7B/sha%7D",
        "clone_url": "https://github.com/darosior/bitcoin.git",
        "hooks_url": "https://api.github.com/repos/darosior/bitcoin/hooks",
        "svn_url": "https://github.com/darosior/bitcoin",
        "homepage": "https://bitcoincore.org/en/download",
        "language": "C++",
        "forks_count": 0,
        "stargazers_count": 2,
        "watchers_count": 2,
        "size": 216031,
        "default_branch": "master",
        "open_issues_count": 0,
        "is_template": false,
        "topics": [],
        "has_issues": false,
        "has_projects": true,
        "has_wiki": false,
        "has_pages": false,
        "has_downloads": false,
        "archived": false,
        "disabled": false,
        "visibility": "public",
        "pushed_at": "2023-05-16T18:02:44Z",
        "created_at": "2019-02-02T19:20:27Z",
        "updated_at": "2023-05-05T11:25:14Z",
        "license": {
          "key": "mit",
          "name": "MIT License",
          "node_id": "MDc6TGljZW5zZTEz",
          "spdx_id": "MIT",
          "url": "https://api.github.com/licenses/mit",
          "html_url": null,
          "description": null,
          "implementation": null,
          "permissions": null,
          "conditions": null,
          "limitations": null,
          "body": null,
          "featured": null
        }
      }
    },
    "base": {
      "label": "bitcoin:master",
      "ref": "master",
      "sha": "d8f982603722590f6be7578591390bcc8a459c18",
      "user": {
        "login": "bitcoin",
        "id": 528860,
        "node_id": "MDEyOk9yZ2FuaXphdGlvbjUyODg2MA==",
        "avatar_url": "https://avatars.githubusercontent.com/u/528860?v=4",
        "gravatar_id": "",
        "url": "https://api.github.com/users/bitcoin",
        "html_url": "https://github.com/bitcoin",
        "followers_url": "https://api.github.com/users/bitcoin/followers",
        "following_url": "https://api.github.com/users/bitcoin/following%7B/other_user%7D",
        "gists_url": "https://api.github.com/users/bitcoin/gists%7B/gist_id%7D",
        "starred_url": "https://api.github.com/users/bitcoin/starred%7B/owner%7D%7B/repo%7D",
        "subscriptions_url": "https://api.github.com/users/bitcoin/subscriptions",
        "organizations_url": "https://api.github.com/users/bitcoin/orgs",
        "repos_url": "https://api.github.com/users/bitcoin/repos",
        "events_url": "https://api.github.com/users/bitcoin/events%7B/privacy%7D",
        "received_events_url": "https://api.github.com/users/bitcoin/received_events",
        "type": "Organization",
        "site_admin": false
      },
      "repo": {
        "id": 1181927,
        "node_id": "MDEwOlJlcG9zaXRvcnkxMTgxOTI3",
        "name": "bitcoin",
        "full_name": "bitcoin/bitcoin",
        "owner": {
          "login": "bitcoin",
          "id": 528860,
          "node_id": "MDEyOk9yZ2FuaXphdGlvbjUyODg2MA==",
          "avatar_url": "https://avatars.githubusercontent.com/u/528860?v=4",
          "gravatar_id": "",
          "url": "https://api.github.com/users/bitcoin",
          "html_url": "https://github.com/bitcoin",
          "followers_url": "https://api.github.com/users/bitcoin/followers",
          "following_url": "https://api.github.com/users/bitcoin/following%7B/other_user%7D",
          "gists_url": "https://api.github.com/users/bitcoin/gists%7B/gist_id%7D",
          "starred_url": "https://api.github.com/users/bitcoin/starred%7B/owner%7D%7B/repo%7D",
          "subscriptions_url": "https://api.github.com/users/bitcoin/subscriptions",
          "organizations_url": "https://api.github.com/users/bitcoin/orgs",
          "repos_url": "https://api.github.com/users/bitcoin/repos",
          "events_url": "https://api.github.com/users/bitcoin/events%7B/privacy%7D",
          "received_events_url": "https://api.github.com/users/bitcoin/received_events",
          "type": "Organization",
          "site_admin": false
        },
        "private": false,
        "html_url": "https://github.com/bitcoin/bitcoin",
        "description": "Bitcoin Core integration/staging tree",
        "fork": false,
        "url": "https://api.github.com/repos/bitcoin/bitcoin",
        "archive_url": "https://api.github.com/repos/bitcoin/bitcoin/%7Barchive_format%7D%7B/ref%7D",
        "assignees_url": "https://api.github.com/repos/bitcoin/bitcoin/assignees%7B/user%7D",
        "blobs_url": "https://api.github.com/repos/bitcoin/bitcoin/git/blobs%7B/sha%7D",
        "branches_url": "https://api.github.com/repos/bitcoin/bitcoin/branches%7B/branch%7D",
        "collaborators_url": "https://api.github.com/repos/bitcoin/bitcoin/collaborators%7B/collaborator%7D",
        "comments_url": "https://api.github.com/repos/bitcoin/bitcoin/comments%7B/number%7D",
        "commits_url": "https://api.github.com/repos/bitcoin/bitcoin/commits%7B/sha%7D",
        "compare_url": "https://api.github.com/repos/bitcoin/bitcoin/compare/%7Bbase%7D...%7Bhead%7D",
        "contents_url": "https://api.github.com/repos/bitcoin/bitcoin/contents/%7B+path%7D",
        "contributors_url": "https://api.github.com/repos/bitcoin/bitcoin/contributors",
        "deployments_url": "https://api.github.com/repos/bitcoin/bitcoin/deployments",
        "downloads_url": "https://api.github.com/repos/bitcoin/bitcoin/downloads",
        "events_url": "https://api.github.com/repos/bitcoin/bitcoin/events",
        "forks_url": "https://api.github.com/repos/bitcoin/bitcoin/forks",
        "git_commits_url": "https://api.github.com/repos/bitcoin/bitcoin/git/commits%7B/sha%7D",
        "git_refs_url": "https://api.github.com/repos/bitcoin/bitcoin/git/refs%7B/sha%7D",
        "git_tags_url": "https://api.github.com/repos/bitcoin/bitcoin/git/tags%7B/sha%7D",
        "git_url": "git://github.com/bitcoin/bitcoin.git",
        "issue_comment_url": "https://api.github.com/repos/bitcoin/bitcoin/issues/comments%7B/number%7D",
        "issue_events_url": "https://api.github.com/repos/bitcoin/bitcoin/issues/events%7B/number%7D",
        "issues_url": "https://api.github.com/repos/bitcoin/bitcoin/issues%7B/number%7D",
        "keys_url": "https://api.github.com/repos/bitcoin/bitcoin/keys%7B/key_id%7D",
        "labels_url": "https://api.github.com/repos/bitcoin/bitcoin/labels%7B/name%7D",
        "languages_url": "https://api.github.com/repos/bitcoin/bitcoin/languages",
        "merges_url": "https://api.github.com/repos/bitcoin/bitcoin/merges",
        "milestones_url": "https://api.github.com/repos/bitcoin/bitcoin/milestones%7B/number%7D",
        "notifications_url": "https://api.github.com/repos/bitcoin/bitcoin/notifications%7B?since,all,participating}",
        "pulls_url": "https://api.github.com/repos/bitcoin/bitcoin/pulls%7B/number%7D",
        "releases_url": "https://api.github.com/repos/bitcoin/bitcoin/releases%7B/id%7D",
        "ssh_url": "git@github.com:bitcoin/bitcoin.git",
        "stargazers_url": "https://api.github.com/repos/bitcoin/bitcoin/stargazers",
        "statuses_url": "https://api.github.com/repos/bitcoin/bitcoin/statuses/%7Bsha%7D",
        "subscribers_url": "https://api.github.com/repos/bitcoin/bitcoin/subscribers",
        "subscription_url": "https://api.github.com/repos/bitcoin/bitcoin/subscription",
        "tags_url": "https://api.github.com/repos/bitcoin/bitcoin/tags",
        "teams_url": "https://api.github.com/repos/bitcoin/bitcoin/teams",
        "trees_url": "https://api.github.com/repos/bitcoin/bitcoin/git/trees%7B/sha%7D",
        "clone_url": "https://github.com/bitcoin/bitcoin.git",
        "hooks_url": "https://api.github.com/repos/bitcoin/bitcoin/hooks",
        "svn_url": "https://github.com/bitcoin/bitcoin",
        "homepage": "https://bitcoincore.org/en/download",
        "language": "C++",
        "forks_count": 34324,
        "stargazers_count": 69818,
        "watchers_count": 69818,
        "size": 233879,
        "default_branch": "master",
        "open_issues_count": 627,
        "is_template": false,
        "topics": [
          "bitcoin",
          "c-plus-plus",
          "cryptocurrency",
          "cryptography",
          "p2p"
        ],
        "has_issues": true,
        "has_projects": true,
        "has_wiki": false,
        "has_pages": false,
        "has_downloads": false,
        "archived": false,
        "disabled": false,
        "visibility": "public",
        "pushed_at": "2023-06-07T07:15:46Z",
        "created_at": "2010-12-19T15:16:43Z",
        "updated_at": "2023-06-07T06:49:43Z",
        "license": {
          "key": "mit",
          "name": "MIT License",
          "node_id": "MDc6TGljZW5zZTEz",
          "spdx_id": "MIT",
          "url": "https://api.github.com/licenses/mit",
          "html_url": null,
          "description": null,
          "implementation": null,
          "permissions": null,
          "conditions": null,
          "limitations": null,
          "body": null,
          "featured": null
        }
      }
    },
    "_links": {
      "self": {
        "href": "https://api.github.com/repos/bitcoin/bitcoin/pulls/26573"
      }
    },
    "author_association": "MEMBER",
    "draft": true,
    "additions": 322,
    "deletions": 173,
    "changed_files": 11,
    "commits": 4,
    "review_comments": 0,
    "comments": 7
  },
  "events": [
    {
      "event": "commented",
      "id": 1327408486,
      "node_id": "IC_kwDOABII585PHqVm",
      "url": "https://api.github.com/repos/bitcoin/bitcoin/issues/comments/1327408486",
      "actor": {
        "login": "DrahtBot",
        "id": 39886733,
        "node_id": "MDQ6VXNlcjM5ODg2NzMz",
        "avatar_url": "https://avatars.githubusercontent.com/u/39886733?v=4",
        "gravatar_id": "",
        "url": "https://api.github.com/users/DrahtBot",
        "html_url": "https://github.com/DrahtBot",
        "followers_url": "https://api.github.com/users/DrahtBot/followers",
        "following_url": "https://api.github.com/users/DrahtBot/following%7B/other_user%7D",
        "gists_url": "https://api.github.com/users/DrahtBot/gists%7B/gist_id%7D",
        "starred_url": "https://api.github.com/users/DrahtBot/starred%7B/owner%7D%7B/repo%7D",
        "subscriptions_url": "https://api.github.com/users/DrahtBot/subscriptions",
        "organizations_url": "https://api.github.com/users/DrahtBot/orgs",
        "repos_url": "https://api.github.com/users/DrahtBot/repos",
        "events_url": "https://api.github.com/users/DrahtBot/events%7B/privacy%7D",
        "received_events_url": "https://api.github.com/users/DrahtBot/received_events",
        "type": "User",
        "site_admin": false
      },
      "commit_id": null,
      "commit_url": null,
      "created_at": "2022-11-25T12:22:01Z",
      "updated_at": "2023-02-05T22:54:42Z",
      "author_association": "MEMBER",
      "body": "<!--e57a25ab6845829454e8d69fc972939a-->\n\nThe following sections might be updated with supplementary metadata relevant to reviewers and maintainers.\n\n<!--021abf342d371248e50ceaed478a90ca-->\n### Reviews\nSee [the guideline](https://github.com/bitcoin/bitcoin/blob/master/CONTRIBUTING.md#code-review) for information on the review process.\n| Type | Reviewers |\n| ---- | --------- |\n| Concept ACK | [achow101](https://github.com/bitcoin/bitcoin/pull/26573#issuecomment-1416543625) |\n\nIf your review is incorrectly listed, please react with ðŸ‘Ž to this comment and the bot will ignore it on the next update.\n<!--174a7506f384e20aa4161008e828411d-->\n### Conflicts\nReviewers, this pull request conflicts with the following ones:\n\n* [#26756](https://github.com/bitcoin/bitcoin/pull/26756) (wallet: Replace `GetBalance()` logic with `AvailableCoins()` by w0xlt)\n* [#26728](https://github.com/bitcoin/bitcoin/pull/26728) (wallet: Have the wallet store the key for automatically generated descriptors by achow101)\n* [#26066](https://github.com/bitcoin/bitcoin/pull/26066) (wallet: Refactor and document CoinControl by aureleoules)\n* [#26032](https://github.com/bitcoin/bitcoin/pull/26032) (wallet: skip R-value signature grinding for external signers by Sjors)\n* [#25907](https://github.com/bitcoin/bitcoin/pull/25907) (wallet: rpc to add automatically generated descriptors by achow101)\n* [#25273](https://github.com/bitcoin/bitcoin/pull/25273) (wallet: Pass through transaction locktime and preset input sequences and scripts to CreateTransaction by achow101)\n* [#24149](https://github.com/bitcoin/bitcoin/pull/24149) (Signing support for Miniscript Descriptors by darosior)\n* [#22838](https://github.com/bitcoin/bitcoin/pull/22838) (descriptors: Be able to specify change and receiving in a single descriptor string by achow101)\n* [#22341](https://github.com/bitcoin/bitcoin/pull/22341) (rpc: add getxpub by Sjors)\n\nIf you consider this pull request important, please also help to review the conflicting pull requests. Ideally, start with the one that should be merged first.\n",
      "user": {
        "login": "DrahtBot",
        "id": 39886733,
        "node_id": "MDQ6VXNlcjM5ODg2NzMz",
        "avatar_url": "https://avatars.githubusercontent.com/u/39886733?v=4",
        "gravatar_id": "",
        "url": "https://api.github.com/users/DrahtBot",
        "html_url": "https://github.com/DrahtBot",
        "followers_url": "https://api.github.com/users/DrahtBot/followers",
        "following_url": "https://api.github.com/users/DrahtBot/following%7B/other_user%7D",
        "gists_url": "https://api.github.com/users/DrahtBot/gists%7B/gist_id%7D",
        "starred_url": "https://api.github.com/users/DrahtBot/starred%7B/owner%7D%7B/repo%7D",
        "subscriptions_url": "https://api.github.com/users/DrahtBot/subscriptions",
        "organizations_url": "https://api.github.com/users/DrahtBot/orgs",
        "repos_url": "https://api.github.com/users/DrahtBot/repos",
        "events_url": "https://api.github.com/users/DrahtBot/events%7B/privacy%7D",
        "received_events_url": "https://api.github.com/users/DrahtBot/received_events",
        "type": "User",
        "site_admin": false
      },
      "html_url": "https://github.com/bitcoin/bitcoin/pull/26573#issuecomment-1327408486",
      "issue_url": "https://api.github.com/repos/bitcoin/bitcoin/issues/26573"
    },
    {
      "event": "renamed",
      "id": 7892796603,
      "node_id": "RTE_lADOABII585XShuMzwAAAAHWcoS7",
      "url": "https://api.github.com/repos/bitcoin/bitcoin/issues/events/7892796603",
      "actor": {
        "login": "darosior",
        "id": 22457751,
        "node_id": "MDQ6VXNlcjIyNDU3NzUx",
        "avatar_url": "https://avatars.githubusercontent.com/u/22457751?v=4",
        "gravatar_id": "",
        "url": "https://api.github.com/users/darosior",
        "html_url": "https://github.com/darosior",
        "followers_url": "https://api.github.com/users/darosior/followers",
        "following_url": "https://api.github.com/users/darosior/following%7B/other_user%7D",
        "gists_url": "https://api.github.com/users/darosior/gists%7B/gist_id%7D",
        "starred_url": "https://api.github.com/users/darosior/starred%7B/owner%7D%7B/repo%7D",
        "subscriptions_url": "https://api.github.com/users/darosior/subscriptions",
        "organizations_url": "https://api.github.com/users/darosior/orgs",
        "repos_url": "https://api.github.com/users/darosior/repos",
        "events_url": "https://api.github.com/users/darosior/events%7B/privacy%7D",
        "received_events_url": "https://api.github.com/users/darosior/received_events",
        "type": "User",
        "site_admin": false
      },
      "commit_id": null,
      "commit_url": null,
      "created_at": "2022-11-25T12:24:43Z",
      "rename": {
        "from": "Taproot over dont under estimate",
        "to": "Wallet: don't underestimate the fees when spending a Taproot output"
      }
    },
    {
      "event": "labeled",
      "id": 7892796824,
      "node_id": "LE_lADOABII585XShuMzwAAAAHWcoWY",
      "url": "https://api.github.com/repos/bitcoin/bitcoin/issues/events/7892796824",
      "actor": {
        "login": "DrahtBot",
        "id": 39886733,
        "node_id": "MDQ6VXNlcjM5ODg2NzMz",
        "avatar_url": "https://avatars.githubusercontent.com/u/39886733?v=4",
        "gravatar_id": "",
        "url": "https://api.github.com/users/DrahtBot",
        "html_url": "https://github.com/DrahtBot",
        "followers_url": "https://api.github.com/users/DrahtBot/followers",
        "following_url": "https://api.github.com/users/DrahtBot/following%7B/other_user%7D",
        "gists_url": "https://api.github.com/users/DrahtBot/gists%7B/gist_id%7D",
        "starred_url": "https://api.github.com/users/DrahtBot/starred%7B/owner%7D%7B/repo%7D",
        "subscriptions_url": "https://api.github.com/users/DrahtBot/subscriptions",
        "organizations_url": "https://api.github.com/users/DrahtBot/orgs",
        "repos_url": "https://api.github.com/users/DrahtBot/repos",
        "events_url": "https://api.github.com/users/DrahtBot/events%7B/privacy%7D",
        "received_events_url": "https://api.github.com/users/DrahtBot/received_events",
        "type": "User",
        "site_admin": false
      },
      "commit_id": null,
      "commit_url": null,
      "created_at": "2022-11-25T12:24:45Z",
      "label": {
        "name": "Wallet",
        "color": "08a781"
      }
    },
    {
      "event": "commented",
      "id": 1328137981,
      "node_id": "IC_kwDOABII585PKcb9",
      "url": "https://api.github.com/repos/bitcoin/bitcoin/issues/comments/1328137981",
      "actor": {
        "login": "luke-jr",
        "id": 1095675,
        "node_id": "MDQ6VXNlcjEwOTU2NzU=",
        "avatar_url": "https://avatars.githubusercontent.com/u/1095675?v=4",
        "gravatar_id": "",
        "url": "https://api.github.com/users/luke-jr",
        "html_url": "https://github.com/luke-jr",
        "followers_url": "https://api.github.com/users/luke-jr/followers",
        "following_url": "https://api.github.com/users/luke-jr/following%7B/other_user%7D",
        "gists_url": "https://api.github.com/users/luke-jr/gists%7B/gist_id%7D",
        "starred_url": "https://api.github.com/users/luke-jr/starred%7B/owner%7D%7B/repo%7D",
        "subscriptions_url": "https://api.github.com/users/luke-jr/subscriptions",
        "organizations_url": "https://api.github.com/users/luke-jr/orgs",
        "repos_url": "https://api.github.com/users/luke-jr/repos",
        "events_url": "https://api.github.com/users/luke-jr/events%7B/privacy%7D",
        "received_events_url": "https://api.github.com/users/luke-jr/received_events",
        "type": "User",
        "site_admin": false
      },
      "commit_id": null,
      "commit_url": null,
      "created_at": "2022-11-27T00:13:56Z",
      "updated_at": "2022-11-27T00:13:56Z",
      "author_association": "MEMBER",
      "body": ">Alternative to https://github.com/bitcoin/bitcoin/pull/23502.\r\n\r\nNot really an alternative, since https://github.com/bitcoin/bitcoin/pull/26567 shouldn't be eligible for backporting, but this is arguably a fix.\r\n\r\nIMO #23502 should still get reviewed & merged first, then let #26567 include this in its refactor.",
      "user": {
        "login": "luke-jr",
        "id": 1095675,
        "node_id": "MDQ6VXNlcjEwOTU2NzU=",
        "avatar_url": "https://avatars.githubusercontent.com/u/1095675?v=4",
        "gravatar_id": "",
        "url": "https://api.github.com/users/luke-jr",
        "html_url": "https://github.com/luke-jr",
        "followers_url": "https://api.github.com/users/luke-jr/followers",
        "following_url": "https://api.github.com/users/luke-jr/following%7B/other_user%7D",
        "gists_url": "https://api.github.com/users/luke-jr/gists%7B/gist_id%7D",
        "starred_url": "https://api.github.com/users/luke-jr/starred%7B/owner%7D%7B/repo%7D",
        "subscriptions_url": "https://api.github.com/users/luke-jr/subscriptions",
        "organizations_url": "https://api.github.com/users/luke-jr/orgs",
        "repos_url": "https://api.github.com/users/luke-jr/repos",
        "events_url": "https://api.github.com/users/luke-jr/events%7B/privacy%7D",
        "received_events_url": "https://api.github.com/users/luke-jr/received_events",
        "type": "User",
        "site_admin": false
      },
      "html_url": "https://github.com/bitcoin/bitcoin/pull/26573#issuecomment-1328137981",
      "issue_url": "https://api.github.com/repos/bitcoin/bitcoin/issues/26573"
    },
    {
      "event": "labeled",
      "id": 7957625876,
      "node_id": "LE_lADOABII585XShuMzwAAAAHaT7wU",
      "url": "https://api.github.com/repos/bitcoin/bitcoin/issues/events/7957625876",
      "actor": {
        "login": "DrahtBot",
        "id": 39886733,
        "node_id": "MDQ6VXNlcjM5ODg2NzMz",
        "avatar_url": "https://avatars.githubusercontent.com/u/39886733?v=4",
        "gravatar_id": "",
        "url": "https://api.github.com/users/DrahtBot",
        "html_url": "https://github.com/DrahtBot",
        "followers_url": "https://api.github.com/users/DrahtBot/followers",
        "following_url": "https://api.github.com/users/DrahtBot/following%7B/other_user%7D",
        "gists_url": "https://api.github.com/users/DrahtBot/gists%7B/gist_id%7D",
        "starred_url": "https://api.github.com/users/DrahtBot/starred%7B/owner%7D%7B/repo%7D",
        "subscriptions_url": "https://api.github.com/users/DrahtBot/subscriptions",
        "organizations_url": "https://api.github.com/users/DrahtBot/orgs",
        "repos_url": "https://api.github.com/users/DrahtBot/repos",
        "events_url": "https://api.github.com/users/DrahtBot/events%7B/privacy%7D",
        "received_events_url": "https://api.github.com/users/DrahtBot/received_events",
        "type": "User",
        "site_admin": false
      },
      "commit_id": null,
      "commit_url": null,
      "created_at": "2022-12-05T18:09:38Z",
      "label": {
        "name": "Needs rebase",
        "color": "cccccc"
      }
    },
    {
      "event": "commented",
      "id": 1416543625,
      "node_id": "IC_kwDOABII585Ubr2J",
      "url": "https://api.github.com/repos/bitcoin/bitcoin/issues/comments/1416543625",
      "actor": {
        "login": "achow101",
        "id": 3782274,
        "node_id": "MDQ6VXNlcjM3ODIyNzQ=",
        "avatar_url": "https://avatars.githubusercontent.com/u/3782274?v=4",
        "gravatar_id": "",
        "url": "https://api.github.com/users/achow101",
        "html_url": "https://github.com/achow101",
        "followers_url": "https://api.github.com/users/achow101/followers",
        "following_url": "https://api.github.com/users/achow101/following%7B/other_user%7D",
        "gists_url": "https://api.github.com/users/achow101/gists%7B/gist_id%7D",
        "starred_url": "https://api.github.com/users/achow101/starred%7B/owner%7D%7B/repo%7D",
        "subscriptions_url": "https://api.github.com/users/achow101/subscriptions",
        "organizations_url": "https://api.github.com/users/achow101/orgs",
        "repos_url": "https://api.github.com/users/achow101/repos",
        "events_url": "https://api.github.com/users/achow101/events%7B/privacy%7D",
        "received_events_url": "https://api.github.com/users/achow101/received_events",
        "type": "User",
        "site_admin": false
      },
      "commit_id": null,
      "commit_url": null,
      "created_at": "2023-02-04T00:02:05Z",
      "updated_at": "2023-02-04T00:02:05Z",
      "author_association": "MEMBER",
      "body": "Concept ACK",
      "user": {
        "login": "achow101",
        "id": 3782274,
        "node_id": "MDQ6VXNlcjM3ODIyNzQ=",
        "avatar_url": "https://avatars.githubusercontent.com/u/3782274?v=4",
        "gravatar_id": "",
        "url": "https://api.github.com/users/achow101",
        "html_url": "https://github.com/achow101",
        "followers_url": "https://api.github.com/users/achow101/followers",
        "following_url": "https://api.github.com/users/achow101/following%7B/other_user%7D",
        "gists_url": "https://api.github.com/users/achow101/gists%7B/gist_id%7D",
        "starred_url": "https://api.github.com/users/achow101/starred%7B/owner%7D%7B/repo%7D",
        "subscriptions_url": "https://api.github.com/users/achow101/subscriptions",
        "organizations_url": "https://api.github.com/users/achow101/orgs",
        "repos_url": "https://api.github.com/users/achow101/repos",
        "events_url": "https://api.github.com/users/achow101/events%7B/privacy%7D",
        "received_events_url": "https://api.github.com/users/achow101/received_events",
        "type": "User",
        "site_admin": false
      },
      "html_url": "https://github.com/bitcoin/bitcoin/pull/26573#issuecomment-1416543625",
      "issue_url": "https://api.github.com/repos/bitcoin/bitcoin/issues/26573"
    },
    {
      "event": "committed",
      "id": null,
      "node_id": "C_kwDOABII59oAKGY4YTBmYzJjNzUzNzk0NTk5OGM5Y2M5NGQ0YTBlM2U1YTNmN2E0YzY",
      "url": "https://api.github.com/repos/bitcoin/bitcoin/git/commits/f8a0fc2c7537945998c9cc94d4a0e3e5a3f7a4c6",
      "actor": null,
      "commit_id": null,
      "commit_url": null,
      "created_at": null,
      "html_url": "https://github.com/bitcoin/bitcoin/commit/f8a0fc2c7537945998c9cc94d4a0e3e5a3f7a4c6",
      "tree": {
        "sha": "a9fdfb21ce36487ce795beaf83f72c9e416bb000",
        "url": "https://api.github.com/repos/bitcoin/bitcoin/git/trees/a9fdfb21ce36487ce795beaf83f72c9e416bb000"
      },
      "verification": {
        "verified": true,
        "reason": "valid",
        "payload": "tree a9fdfb21ce36487ce795beaf83f72c9e416bb000\nparent d8f982603722590f6be7578591390bcc8a459c18\nauthor Antoine Poinsot <darosior@protonmail.com> 1660926834 +0200\ncommitter Antoine Poinsot <darosior@protonmail.com> 1675619840 +0100\n\ndescriptor: introduce a method to get the satisfaction size\n\nIn the wallet code, we are currently estimating the size of a signed\ninput by doing a dry run of the signing logic. This is unnecessary as\nall outputs we are able to sign for can be represented by a descriptor,\nand we can derive the size of a satisfaction (\"signature\") from the\ndescriptor itself directly.\nIn addition, this approach does not scale: getting the size of a\nsatisfaction through a dry run of the signing logic is only possible for\nthe most basic scripts.\n\nThis commit introduces the computation of the size of satisfaction per\ndescriptor. It's a bit intricate for 2 main reasons:\n- We want to conserve the behaviour of the current dry-run logic used by\n  the wallet that sometimes assumes ECDSA signatures will be low-r,\n  sometimes not (when we don't create them).\n- We need to account for the witness discount. A single descriptor may\n  sometimes benefit of it, sometimes not (for instance `pk()` if used as\n  top-level versus if used inside `wsh()`).\n",
        "signature": "-----BEGIN PGP SIGNATURE-----\n\niQGzBAABCgAdFiEEWQtykmla/6W2csuy4T/BRc0/QwQFAmPf7gAACgkQ4T/BRc0/\nQwRQXwwAyAYl+CryfCKdCJ9RBT3rn0OfUqAWh/n9xii2awfy8/7uOOCXxF2HYKWk\nTrVblKjaL34WfxKVVAr2YfFM2aHiMW3Nqv9T0bfmohk+4NQH6RWimX1IFOJLIR9x\n9tGYen3ApAm2bbE2nGpJtstIwt5OwlEk8RcwWReFwP4qzxa7GMqdzMPrOx5mxWZ5\n0OWy580ELYmqa6/SPieD3URoFcrGKl2gAeqsrW2cP77csz9tEI84FHQAmyDcAt03\nRKnnrnQ+UvC0VPkbpUX3a43WowVyrNfsGxrEtx6B9irbeF85MZeBwBKtQaJugBcv\n5Dp9rqqQp6SofolzMY0FOOsEesI722gBvZWhfJNCULHLb4/xOBve7L68E4C4dK1D\nSmsW3/6k01hJQNr8oEntcRKoeVPdwu+NbCgpK7+32jONjMczFMmGRCjFvIV4jAJq\nnQBL1AgXY3de9HC3JqNzu/gqNZ5mG1T5wXfjUApNKMNJnqsFWW1Jg5jh1OZxd97S\nWrBX6nGo\n=HDBF\n-----END PGP SIGNATURE-----"
      },
      "parents": [
        {
          "url": "https://api.github.com/repos/bitcoin/bitcoin/git/commits/d8f982603722590f6be7578591390bcc8a459c18",
          "sha": "d8f982603722590f6be7578591390bcc8a459c18",
          "html_url": "https://github.com/bitcoin/bitcoin/commit/d8f982603722590f6be7578591390bcc8a459c18"
        }
      ],
      "message": "descriptor: introduce a method to get the satisfaction size\n\nIn the wallet code, we are currently estimating the size of a signed\ninput by doing a dry run of the signing logic. This is unnecessary as\nall outputs we are able to sign for can be represented by a descriptor,\nand we can derive the size of a satisfaction (\"signature\") from the\ndescriptor itself directly.\nIn addition, this approach does not scale: getting the size of a\nsatisfaction through a dry run of the signing logic is only possible for\nthe most basic scripts.\n\nThis commit introduces the computation of the size of satisfaction per\ndescriptor. It's a bit intricate for 2 main reasons:\n- We want to conserve the behaviour of the current dry-run logic used by\n  the wallet that sometimes assumes ECDSA signatures will be low-r,\n  sometimes not (when we don't create them).\n- We need to account for the witness discount. A single descriptor may\n  sometimes benefit of it, sometimes not (for instance `pk()` if used as\n  top-level versus if used inside `wsh()`).",
      "committer": {
        "name": "Antoine Poinsot",
        "email": "darosior@protonmail.com",
        "date": "2023-02-05T17:57:20Z"
      },
      "author": {
        "name": "Antoine Poinsot",
        "email": "darosior@protonmail.com",
        "date": "2022-08-19T16:33:54Z"
      },
      "sha": "f8a0fc2c7537945998c9cc94d4a0e3e5a3f7a4c6"
    },
    {
      "event": "committed",
      "id": null,
      "node_id": "C_kwDOABII59oAKDg5NmE1NjBhYmVmNTJmNDFkYmMxMmUzZmVkY2Q4NmFiNGE2NTdiMDY",
      "url": "https://api.github.com/repos/bitcoin/bitcoin/git/commits/896a560abef52f41dbc12e3fedcd86ab4a657b06",
      "actor": null,
      "commit_id": null,
      "commit_url": null,
      "created_at": null,
      "html_url": "https://github.com/bitcoin/bitcoin/commit/896a560abef52f41dbc12e3fedcd86ab4a657b06",
      "tree": {
        "sha": "df5262a8fdbbfe3c7cd2ad26178c1e2b1d07867e",
        "url": "https://api.github.com/repos/bitcoin/bitcoin/git/trees/df5262a8fdbbfe3c7cd2ad26178c1e2b1d07867e"
      },
      "verification": {
        "verified": true,
        "reason": "valid",
        "payload": "tree df5262a8fdbbfe3c7cd2ad26178c1e2b1d07867e\nparent f8a0fc2c7537945998c9cc94d4a0e3e5a3f7a4c6\nauthor Antoine Poinsot <darosior@protonmail.com> 1660926900 +0200\ncommitter Antoine Poinsot <darosior@protonmail.com> 1675619841 +0100\n\nwallet: use descriptor satisfaction size to estimate inputs size\n\nInstead of using the dummysigner to compute a placeholder satisfaction,\ninfer a descriptor on the scriptPubKey of the coin being spent and use\nthe estimation of the satisfaction size given by the descriptor\ndirectly.\n\nNote this (almost, see next paragraph) exactly conserves the previous\nbehaviour. For instance CalculateMaximumSignedInputSize was previously\nassuming the input to be spent in a transaction that spends at least one\nSegwit coin, since it was always accounting for the serialization of the\nnumber of witness elements.\n\nIn this commit we use a placeholder for the size of the serialization of\nthe witness stack size (1 byte). Since the logic in this commit is\nalready tricky enough to review, and that it is only a very tiny\napproximation not observable through the existing tests, it is addressed\nin the next commit.\n",
        "signature": "-----BEGIN PGP SIGNATURE-----\n\niQGzBAABCgAdFiEEWQtykmla/6W2csuy4T/BRc0/QwQFAmPf7gEACgkQ4T/BRc0/\nQwSEAgv8CqPU8WAEFBB7RiygdnUclxLON/57E7Mjr6//AtwQTEnpagcRAaxUUASu\nDdD5PsWvri+RvtbWTQ/IDbOP7vpk9pU7aKufYRzB1M6qvHo3ke5WvSYnUBaLXnzA\n5Y4NQ8e3YcsV5yvYZUzwy70eitY6hT20zDrjzCl8oO9i2SugUQQP8qCplS8ew6WF\nHmKKYdzXY6xLFCxvvLRFwvItb2m+HsQltZLChFN7y6abYXVXsLeo76ZX6z6YZyQd\nhqCCII6XJT0SpqMEyndnEPEvJ21NoyT4j27+zTGQwcjnMprtxRoidZOdOGH1NMfx\n0ZhTR84P9LEMIJPDHrkQyKQ4jBiKxji4MOLqpPxAXseHBTWW6uf/2M18T/79pI4C\nL1IIaM4Cw5LwJ35Q5TXFW+46D2eWB8DUIOb+Bzwwc3Uo8EfjHWd+5gbZwkyDPcFz\njLkvxVAcXUheWa5lfw1YEspAkvbvTqWE3Nu+PwfRLAVa3Lnt9kybUo4gRulpFmpy\nVeKxgSYJ\n=KmOI\n-----END PGP SIGNATURE-----"
      },
      "parents": [
        {
          "url": "https://api.github.com/repos/bitcoin/bitcoin/git/commits/f8a0fc2c7537945998c9cc94d4a0e3e5a3f7a4c6",
          "sha": "f8a0fc2c7537945998c9cc94d4a0e3e5a3f7a4c6",
          "html_url": "https://github.com/bitcoin/bitcoin/commit/f8a0fc2c7537945998c9cc94d4a0e3e5a3f7a4c6"
        }
      ],
      "message": "wallet: use descriptor satisfaction size to estimate inputs size\n\nInstead of using the dummysigner to compute a placeholder satisfaction,\ninfer a descriptor on the scriptPubKey of the coin being spent and use\nthe estimation of the satisfaction size given by the descriptor\ndirectly.\n\nNote this (almost, see next paragraph) exactly conserves the previous\nbehaviour. For instance CalculateMaximumSignedInputSize was previously\nassuming the input to be spent in a transaction that spends at least one\nSegwit coin, since it was always accounting for the serialization of the\nnumber of witness elements.\n\nIn this commit we use a placeholder for the size of the serialization of\nthe witness stack size (1 byte). Since the logic in this commit is\nalready tricky enough to review, and that it is only a very tiny\napproximation not observable through the existing tests, it is addressed\nin the next commit.",
      "committer": {
        "name": "Antoine Poinsot",
        "email": "darosior@protonmail.com",
        "date": "2023-02-05T17:57:21Z"
      },
      "author": {
        "name": "Antoine Poinsot",
        "email": "darosior@protonmail.com",
        "date": "2022-08-19T16:35:00Z"
      },
      "sha": "896a560abef52f41dbc12e3fedcd86ab4a657b06"
    },
    {
      "event": "committed",
      "id": null,
      "node_id": "C_kwDOABII59oAKDk2Nzc5NWNlZTRhZTk1OTRkMWFiYzZkMmVjMDg1ZGFjOGM1YmY0NjA",
      "url": "https://api.github.com/repos/bitcoin/bitcoin/git/commits/967795cee4ae9594d1abc6d2ec085dac8c5bf460",
      "actor": null,
      "commit_id": null,
      "commit_url": null,
      "created_at": null,
      "html_url": "https://github.com/bitcoin/bitcoin/commit/967795cee4ae9594d1abc6d2ec085dac8c5bf460",
      "tree": {
        "sha": "751b1fe2b794149408f16f4900772bc5f135afed",
        "url": "https://api.github.com/repos/bitcoin/bitcoin/git/trees/751b1fe2b794149408f16f4900772bc5f135afed"
      },
      "verification": {
        "verified": true,
        "reason": "valid",
        "payload": "tree 751b1fe2b794149408f16f4900772bc5f135afed\nparent 896a560abef52f41dbc12e3fedcd86ab4a657b06\nauthor Antoine Poinsot <darosior@protonmail.com> 1669369555 +0100\ncommitter Antoine Poinsot <darosior@protonmail.com> 1675619841 +0100\n\nwallet: accurately account for the size of the witness stack\n\nWhen estimating the maximum size of an input, we were assuming the\nnumber of elements on the witness stack could be encode in a single\nbyte. This is a valid approximation for now since none of our currently\n*solvable* descriptor may have a satisfaction with more than 253\nelements on the stack. But it won't be the case anymore when we make\nMiniscript descriptor solvable for instance.\n",
        "signature": "-----BEGIN PGP SIGNATURE-----\n\niQGzBAABCgAdFiEEWQtykmla/6W2csuy4T/BRc0/QwQFAmPf7gEACgkQ4T/BRc0/\nQwRenAwA2eSPKPtzx1/yUi9EOZpx/RILNKnxTCHIYBbj/h4TIROYbZatash/Dm4e\nzMO06SBAyoOnDDILDecc2H0KQwnag6IDrEfLZLpQ/fs1phApFidbTCk7VAGHRPIP\nxb80LURLy2NClIqbIX8KJ3cwfsuqOIaih/4mLN0hJTpL7kxWmq7TN6LPVw0umS/I\nXCWiuLYWvHBkwq8ua+2myGkaIk6BjtTyGuw8pLY4DKhNHOY3xrmhO2QDcqqndynG\n/US8koI8reDhnu7PDZc5keboSGOcqfWsXum5Jontdsw6ng4PYb6ZlHlGRjuIoofF\nmV/6QKdzwuJ68nIKcAzxKdneINpu4EhLwnnkes2eDsFALoufNqSfrUilwHczqnrt\nFDSwvOAk9yYj8jk1FIk1k9Bgwf6h+P6X82hIwOEb280H+1Sczog5zQX94abC6LwI\nCeIBgkWHNrlHcT6PtelRXnwCBad2mHAxG2+tuw5/sOO+6QHZrVhFJ4dmf3wICToX\nI40loYlh\n=XGC1\n-----END PGP SIGNATURE-----"
      },
      "parents": [
        {
          "url": "https://api.github.com/repos/bitcoin/bitcoin/git/commits/896a560abef52f41dbc12e3fedcd86ab4a657b06",
          "sha": "896a560abef52f41dbc12e3fedcd86ab4a657b06",
          "html_url": "https://github.com/bitcoin/bitcoin/commit/896a560abef52f41dbc12e3fedcd86ab4a657b06"
        }
      ],
      "message": "wallet: accurately account for the size of the witness stack\n\nWhen estimating the maximum size of an input, we were assuming the\nnumber of elements on the witness stack could be encode in a single\nbyte. This is a valid approximation for now since none of our currently\n*solvable* descriptor may have a satisfaction with more than 253\nelements on the stack. But it won't be the case anymore when we make\nMiniscript descriptor solvable for instance.",
      "committer": {
        "name": "Antoine Poinsot",
        "email": "darosior@protonmail.com",
        "date": "2023-02-05T17:57:21Z"
      },
      "author": {
        "name": "Antoine Poinsot",
        "email": "darosior@protonmail.com",
        "date": "2022-11-25T09:45:55Z"
      },
      "sha": "967795cee4ae9594d1abc6d2ec085dac8c5bf460"
    },
    {
      "event": "committed",
      "id": null,
      "node_id": "C_kwDOABII59oAKDA4ZjI4OGZkZGMzM2Y2ZmYzY2Y4OWVmNDk2MDU5NGMwYTI4ZGYyZjU",
      "url": "https://api.github.com/repos/bitcoin/bitcoin/git/commits/08f288fddc33f6ff3cf89ef4960594c0a28df2f5",
      "actor": null,
      "commit_id": null,
      "commit_url": null,
      "created_at": null,
      "html_url": "https://github.com/bitcoin/bitcoin/commit/08f288fddc33f6ff3cf89ef4960594c0a28df2f5",
      "tree": {
        "sha": "83287a853311701c3a4f89b51e0eee31898d5f64",
        "url": "https://api.github.com/repos/bitcoin/bitcoin/git/trees/83287a853311701c3a4f89b51e0eee31898d5f64"
      },
      "verification": {
        "verified": true,
        "reason": "valid",
        "payload": "tree 83287a853311701c3a4f89b51e0eee31898d5f64\nparent 967795cee4ae9594d1abc6d2ec085dac8c5bf460\nauthor Antoine Poinsot <darosior@protonmail.com> 1669375034 +0100\ncommitter Antoine Poinsot <darosior@protonmail.com> 1675620354 +0100\n\ndescriptor: don't underestimate the size of a Taproot spend\n\nWe were previously assuming the key path was always used for size\nestimation, which could lead to underestimate the fees if one of the\nscript paths was used in the end.\n\nInstead, overestimate: use the most expensive between the key path and\nall existing script paths.\n\nThe functional test changes were authored by Andrew Chow for PR 23502.\nCo-Authored-by: Andrew Chow <achow101-github@achow101.com>\n",
        "signature": "-----BEGIN PGP SIGNATURE-----\n\niQGzBAABCgAdFiEEWQtykmla/6W2csuy4T/BRc0/QwQFAmPf8AQACgkQ4T/BRc0/\nQwRBzAv/YHbPFtprnW2XfIhMsTE4EOaXGJJmb3fKKCzGACmyGaGH8ElfFjbV18sz\n+CoGw0T5Qv9Ifi9f84NWuQtYo2u6jBxmkmPYzXFvPq8grJJA7YgIoIGn+7h8Wru2\nse1PMatu8Cqv6jGCm860Vd8UWcsArxP5If5L1hQZ/r8D53PdsoLMUenfDq93vRWx\nNrs/X+uvyBPlQMf5r2IuUFCuVrC1b1cm6y9yosGgsKIdSL0KJaKWInTYkwvNPLhX\n4EfkyV7FRHyzp4i+VapvqBU4jP7PFfi1uwKUVWaQMhDxa+mX6f66gCiWrYrqkwKH\n6HV1qMllgrB8MXI7idulen5qyicqLGYUQJ797lNgAHjBi4exRRe3iVQ3rtXWht5m\n83oy98Hx50BEpKBMeOpvNVi+rmsRpo0txK5K6ilbKj5lcZ6dKT3DCuzeELvB87Fp\n82MM0vnm0hdqWBBTdp1+jiH8xsnRyUsxTn36d2KS9ytreHyXGH3GeyljeA+0FnKH\nywINqC5d\n=osrJ\n-----END PGP SIGNATURE-----"
      },
      "parents": [
        {
          "url": "https://api.github.com/repos/bitcoin/bitcoin/git/commits/967795cee4ae9594d1abc6d2ec085dac8c5bf460",
          "sha": "967795cee4ae9594d1abc6d2ec085dac8c5bf460",
          "html_url": "https://github.com/bitcoin/bitcoin/commit/967795cee4ae9594d1abc6d2ec085dac8c5bf460"
        }
      ],
      "message": "descriptor: don't underestimate the size of a Taproot spend\n\nWe were previously assuming the key path was always used for size\nestimation, which could lead to underestimate the fees if one of the\nscript paths was used in the end.\n\nInstead, overestimate: use the most expensive between the key path and\nall existing script paths.\n\nThe functional test changes were authored by Andrew Chow for PR 23502.\nCo-Authored-by: Andrew Chow <achow101-github@achow101.com>",
      "committer": {
        "name": "Antoine Poinsot",
        "email": "darosior@protonmail.com",
        "date": "2023-02-05T18:05:54Z"
      },
      "author": {
        "name": "Antoine Poinsot",
        "email": "darosior@protonmail.com",
        "date": "2022-11-25T11:17:14Z"
      },
      "sha": "08f288fddc33f6ff3cf89ef4960594c0a28df2f5"
    },
    {
      "event": "head_ref_force_pushed",
      "id": 8441013804,
      "node_id": "HRFPE_lADOABII585XShuMzwAAAAH3H6Ys",
      "url": "https://api.github.com/repos/bitcoin/bitcoin/issues/events/8441013804",
      "actor": {
        "login": "darosior",
        "id": 22457751,
        "node_id": "MDQ6VXNlcjIyNDU3NzUx",
        "avatar_url": "https://avatars.githubusercontent.com/u/22457751?v=4",
        "gravatar_id": "",
        "url": "https://api.github.com/users/darosior",
        "html_url": "https://github.com/darosior",
        "followers_url": "https://api.github.com/users/darosior/followers",
        "following_url": "https://api.github.com/users/darosior/following%7B/other_user%7D",
        "gists_url": "https://api.github.com/users/darosior/gists%7B/gist_id%7D",
        "starred_url": "https://api.github.com/users/darosior/starred%7B/owner%7D%7B/repo%7D",
        "subscriptions_url": "https://api.github.com/users/darosior/subscriptions",
        "organizations_url": "https://api.github.com/users/darosior/orgs",
        "repos_url": "https://api.github.com/users/darosior/repos",
        "events_url": "https://api.github.com/users/darosior/events%7B/privacy%7D",
        "received_events_url": "https://api.github.com/users/darosior/received_events",
        "type": "User",
        "site_admin": false
      },
      "commit_id": null,
      "commit_url": null,
      "created_at": "2023-02-05T18:18:04Z"
    },
    {
      "event": "commented",
      "id": 1418206188,
      "node_id": "IC_kwDOABII585UiBvs",
      "url": "https://api.github.com/repos/bitcoin/bitcoin/issues/comments/1418206188",
      "actor": {
        "login": "darosior",
        "id": 22457751,
        "node_id": "MDQ6VXNlcjIyNDU3NzUx",
        "avatar_url": "https://avatars.githubusercontent.com/u/22457751?v=4",
        "gravatar_id": "",
        "url": "https://api.github.com/users/darosior",
        "html_url": "https://github.com/darosior",
        "followers_url": "https://api.github.com/users/darosior/followers",
        "following_url": "https://api.github.com/users/darosior/following%7B/other_user%7D",
        "gists_url": "https://api.github.com/users/darosior/gists%7B/gist_id%7D",
        "starred_url": "https://api.github.com/users/darosior/starred%7B/owner%7D%7B/repo%7D",
        "subscriptions_url": "https://api.github.com/users/darosior/subscriptions",
        "organizations_url": "https://api.github.com/users/darosior/orgs",
        "repos_url": "https://api.github.com/users/darosior/repos",
        "events_url": "https://api.github.com/users/darosior/events%7B/privacy%7D",
        "received_events_url": "https://api.github.com/users/darosior/received_events",
        "type": "User",
        "site_admin": false
      },
      "commit_id": null,
      "commit_url": null,
      "created_at": "2023-02-05T18:18:15Z",
      "updated_at": "2023-02-05T18:18:15Z",
      "author_association": "MEMBER",
      "body": "Rebased.",
      "user": {
        "login": "darosior",
        "id": 22457751,
        "node_id": "MDQ6VXNlcjIyNDU3NzUx",
        "avatar_url": "https://avatars.githubusercontent.com/u/22457751?v=4",
        "gravatar_id": "",
        "url": "https://api.github.com/users/darosior",
        "html_url": "https://github.com/darosior",
        "followers_url": "https://api.github.com/users/darosior/followers",
        "following_url": "https://api.github.com/users/darosior/following%7B/other_user%7D",
        "gists_url": "https://api.github.com/users/darosior/gists%7B/gist_id%7D",
        "starred_url": "https://api.github.com/users/darosior/starred%7B/owner%7D%7B/repo%7D",
        "subscriptions_url": "https://api.github.com/users/darosior/subscriptions",
        "organizations_url": "https://api.github.com/users/darosior/orgs",
        "repos_url": "https://api.github.com/users/darosior/repos",
        "events_url": "https://api.github.com/users/darosior/events%7B/privacy%7D",
        "received_events_url": "https://api.github.com/users/darosior/received_events",
        "type": "User",
        "site_admin": false
      },
      "html_url": "https://github.com/bitcoin/bitcoin/pull/26573#issuecomment-1418206188",
      "issue_url": "https://api.github.com/repos/bitcoin/bitcoin/issues/26573"
    },
    {
      "event": "unlabeled",
      "id": 8441160436,
      "node_id": "UNLE_lADOABII585XShuMzwAAAAH3IeL0",
      "url": "https://api.github.com/repos/bitcoin/bitcoin/issues/events/8441160436",
      "actor": {
        "login": "DrahtBot",
        "id": 39886733,
        "node_id": "MDQ6VXNlcjM5ODg2NzMz",
        "avatar_url": "https://avatars.githubusercontent.com/u/39886733?v=4",
        "gravatar_id": "",
        "url": "https://api.github.com/users/DrahtBot",
        "html_url": "https://github.com/DrahtBot",
        "followers_url": "https://api.github.com/users/DrahtBot/followers",
        "following_url": "https://api.github.com/users/DrahtBot/following%7B/other_user%7D",
        "gists_url": "https://api.github.com/users/DrahtBot/gists%7B/gist_id%7D",
        "starred_url": "https://api.github.com/users/DrahtBot/starred%7B/owner%7D%7B/repo%7D",
        "subscriptions_url": "https://api.github.com/users/DrahtBot/subscriptions",
        "organizations_url": "https://api.github.com/users/DrahtBot/orgs",
        "repos_url": "https://api.github.com/users/DrahtBot/repos",
        "events_url": "https://api.github.com/users/DrahtBot/events%7B/privacy%7D",
        "received_events_url": "https://api.github.com/users/DrahtBot/received_events",
        "type": "User",
        "site_admin": false
      },
      "commit_id": null,
      "commit_url": null,
      "created_at": "2023-02-05T19:04:55Z",
      "label": {
        "name": "Needs rebase",
        "color": "cccccc"
      }
    },
    {
      "event": "labeled",
      "id": 8535756459,
      "node_id": "LE_lADOABII585XShuMzwAAAAH8xU6r",
      "url": "https://api.github.com/repos/bitcoin/bitcoin/issues/events/8535756459",
      "actor": {
        "login": "DrahtBot",
        "id": 39886733,
        "node_id": "MDQ6VXNlcjM5ODg2NzMz",
        "avatar_url": "https://avatars.githubusercontent.com/u/39886733?v=4",
        "gravatar_id": "",
        "url": "https://api.github.com/users/DrahtBot",
        "html_url": "https://github.com/DrahtBot",
        "followers_url": "https://api.github.com/users/DrahtBot/followers",
        "following_url": "https://api.github.com/users/DrahtBot/following%7B/other_user%7D",
        "gists_url": "https://api.github.com/users/DrahtBot/gists%7B/gist_id%7D",
        "starred_url": "https://api.github.com/users/DrahtBot/starred%7B/owner%7D%7B/repo%7D",
        "subscriptions_url": "https://api.github.com/users/DrahtBot/subscriptions",
        "organizations_url": "https://api.github.com/users/DrahtBot/orgs",
        "repos_url": "https://api.github.com/users/DrahtBot/repos",
        "events_url": "https://api.github.com/users/DrahtBot/events%7B/privacy%7D",
        "received_events_url": "https://api.github.com/users/DrahtBot/received_events",
        "type": "User",
        "site_admin": false
      },
      "commit_id": null,
      "commit_url": null,
      "created_at": "2023-02-16T11:09:54Z",
      "label": {
        "name": "Needs rebase",
        "color": "cccccc"
      }
    },
    {
      "event": "commented",
      "id": 1432920202,
      "node_id": "IC_kwDOABII585VaKCK",
      "url": "https://api.github.com/repos/bitcoin/bitcoin/issues/comments/1432920202",
      "actor": {
        "login": "DrahtBot",
        "id": 39886733,
        "node_id": "MDQ6VXNlcjM5ODg2NzMz",
        "avatar_url": "https://avatars.githubusercontent.com/u/39886733?v=4",
        "gravatar_id": "",
        "url": "https://api.github.com/users/DrahtBot",
        "html_url": "https://github.com/DrahtBot",
        "followers_url": "https://api.github.com/users/DrahtBot/followers",
        "following_url": "https://api.github.com/users/DrahtBot/following%7B/other_user%7D",
        "gists_url": "https://api.github.com/users/DrahtBot/gists%7B/gist_id%7D",
        "starred_url": "https://api.github.com/users/DrahtBot/starred%7B/owner%7D%7B/repo%7D",
        "subscriptions_url": "https://api.github.com/users/DrahtBot/subscriptions",
        "organizations_url": "https://api.github.com/users/DrahtBot/orgs",
        "repos_url": "https://api.github.com/users/DrahtBot/repos",
        "events_url": "https://api.github.com/users/DrahtBot/events%7B/privacy%7D",
        "received_events_url": "https://api.github.com/users/DrahtBot/received_events",
        "type": "User",
        "site_admin": false
      },
      "commit_id": null,
      "commit_url": null,
      "created_at": "2023-02-16T11:09:55Z",
      "updated_at": "2023-02-16T11:09:55Z",
      "author_association": "MEMBER",
      "body": "<!--cf906140f33d8803c4a75a2196329ecb-->\nðŸ™ This pull request conflicts with the target branch and [needs rebase](https://github.com/bitcoin/bitcoin/blob/master/CONTRIBUTING.md#rebasing-changes).\n",
      "user": {
        "login": "DrahtBot",
        "id": 39886733,
        "node_id": "MDQ6VXNlcjM5ODg2NzMz",
        "avatar_url": "https://avatars.githubusercontent.com/u/39886733?v=4",
        "gravatar_id": "",
        "url": "https://api.github.com/users/DrahtBot",
        "html_url": "https://github.com/DrahtBot",
        "followers_url": "https://api.github.com/users/DrahtBot/followers",
        "following_url": "https://api.github.com/users/DrahtBot/following%7B/other_user%7D",
        "gists_url": "https://api.github.com/users/DrahtBot/gists%7B/gist_id%7D",
        "starred_url": "https://api.github.com/users/DrahtBot/starred%7B/owner%7D%7B/repo%7D",
        "subscriptions_url": "https://api.github.com/users/DrahtBot/subscriptions",
        "organizations_url": "https://api.github.com/users/DrahtBot/orgs",
        "repos_url": "https://api.github.com/users/DrahtBot/repos",
        "events_url": "https://api.github.com/users/DrahtBot/events%7B/privacy%7D",
        "received_events_url": "https://api.github.com/users/DrahtBot/received_events",
        "type": "User",
        "site_admin": false
      },
      "html_url": "https://github.com/bitcoin/bitcoin/pull/26573#issuecomment-1432920202",
      "issue_url": "https://api.github.com/repos/bitcoin/bitcoin/issues/26573"
    },
    {
      "event": "commented",
      "id": 1443850979,
      "node_id": "IC_kwDOABII585WD2rj",
      "url": "https://api.github.com/repos/bitcoin/bitcoin/issues/comments/1443850979",
      "actor": {
        "login": "fanquake",
        "id": 863730,
        "node_id": "MDQ6VXNlcjg2MzczMA==",
        "avatar_url": "https://avatars.githubusercontent.com/u/863730?v=4",
        "gravatar_id": "",
        "url": "https://api.github.com/users/fanquake",
        "html_url": "https://github.com/fanquake",
        "followers_url": "https://api.github.com/users/fanquake/followers",
        "following_url": "https://api.github.com/users/fanquake/following%7B/other_user%7D",
        "gists_url": "https://api.github.com/users/fanquake/gists%7B/gist_id%7D",
        "starred_url": "https://api.github.com/users/fanquake/starred%7B/owner%7D%7B/repo%7D",
        "subscriptions_url": "https://api.github.com/users/fanquake/subscriptions",
        "organizations_url": "https://api.github.com/users/fanquake/orgs",
        "repos_url": "https://api.github.com/users/fanquake/repos",
        "events_url": "https://api.github.com/users/fanquake/events%7B/privacy%7D",
        "received_events_url": "https://api.github.com/users/fanquake/received_events",
        "type": "User",
        "site_admin": false
      },
      "commit_id": null,
      "commit_url": null,
      "created_at": "2023-02-24T15:27:48Z",
      "updated_at": "2023-02-24T15:27:48Z",
      "author_association": "MEMBER",
      "body": "Moving this to draft for now, given it's based on #26567.",
      "user": {
        "login": "fanquake",
        "id": 863730,
        "node_id": "MDQ6VXNlcjg2MzczMA==",
        "avatar_url": "https://avatars.githubusercontent.com/u/863730?v=4",
        "gravatar_id": "",
        "url": "https://api.github.com/users/fanquake",
        "html_url": "https://github.com/fanquake",
        "followers_url": "https://api.github.com/users/fanquake/followers",
        "following_url": "https://api.github.com/users/fanquake/following%7B/other_user%7D",
        "gists_url": "https://api.github.com/users/fanquake/gists%7B/gist_id%7D",
        "starred_url": "https://api.github.com/users/fanquake/starred%7B/owner%7D%7B/repo%7D",
        "subscriptions_url": "https://api.github.com/users/fanquake/subscriptions",
        "organizations_url": "https://api.github.com/users/fanquake/orgs",
        "repos_url": "https://api.github.com/users/fanquake/repos",
        "events_url": "https://api.github.com/users/fanquake/events%7B/privacy%7D",
        "received_events_url": "https://api.github.com/users/fanquake/received_events",
        "type": "User",
        "site_admin": false
      },
      "html_url": "https://github.com/bitcoin/bitcoin/pull/26573#issuecomment-1443850979",
      "issue_url": "https://api.github.com/repos/bitcoin/bitcoin/issues/26573"
    },
    {
      "event": "convert_to_draft",
      "id": 8603079663,
      "node_id": "CTDE_lADOABII585XShuMzwAAAAIAyJPv",
      "url": "https://api.github.com/repos/bitcoin/bitcoin/issues/events/8603079663",
      "actor": {
        "login": "fanquake",
        "id": 863730,
        "node_id": "MDQ6VXNlcjg2MzczMA==",
        "avatar_url": "https://avatars.githubusercontent.com/u/863730?v=4",
        "gravatar_id": "",
        "url": "https://api.github.com/users/fanquake",
        "html_url": "https://github.com/fanquake",
        "followers_url": "https://api.github.com/users/fanquake/followers",
        "following_url": "https://api.github.com/users/fanquake/following%7B/other_user%7D",
        "gists_url": "https://api.github.com/users/fanquake/gists%7B/gist_id%7D",
        "starred_url": "https://api.github.com/users/fanquake/starred%7B/owner%7D%7B/repo%7D",
        "subscriptions_url": "https://api.github.com/users/fanquake/subscriptions",
        "organizations_url": "https://api.github.com/users/fanquake/orgs",
        "repos_url": "https://api.github.com/users/fanquake/repos",
        "events_url": "https://api.github.com/users/fanquake/events%7B/privacy%7D",
        "received_events_url": "https://api.github.com/users/fanquake/received_events",
        "type": "User",
        "site_admin": false
      },
      "commit_id": null,
      "commit_url": null,
      "created_at": "2023-02-24T15:27:53Z"
    },
    {
      "event": "commented",
      "id": 1562129950,
      "node_id": "IC_kwDOABII585dHDYe",
      "url": "https://api.github.com/repos/bitcoin/bitcoin/issues/comments/1562129950",
      "actor": {
        "login": "DrahtBot",
        "id": 39886733,
        "node_id": "MDQ6VXNlcjM5ODg2NzMz",
        "avatar_url": "https://avatars.githubusercontent.com/u/39886733?v=4",
        "gravatar_id": "",
        "url": "https://api.github.com/users/DrahtBot",
        "html_url": "https://github.com/DrahtBot",
        "followers_url": "https://api.github.com/users/DrahtBot/followers",
        "following_url": "https://api.github.com/users/DrahtBot/following%7B/other_user%7D",
        "gists_url": "https://api.github.com/users/DrahtBot/gists%7B/gist_id%7D",
        "starred_url": "https://api.github.com/users/DrahtBot/starred%7B/owner%7D%7B/repo%7D",
        "subscriptions_url": "https://api.github.com/users/DrahtBot/subscriptions",
        "organizations_url": "https://api.github.com/users/DrahtBot/orgs",
        "repos_url": "https://api.github.com/users/DrahtBot/repos",
        "events_url": "https://api.github.com/users/DrahtBot/events%7B/privacy%7D",
        "received_events_url": "https://api.github.com/users/DrahtBot/received_events",
        "type": "User",
        "site_admin": false
      },
      "commit_id": null,
      "commit_url": null,
      "created_at": "2023-05-25T01:21:58Z",
      "updated_at": "2023-05-25T01:21:58Z",
      "author_association": "MEMBER",
      "body": "<!--13523179cfe9479db18ec6c5d236f789-->\nThere hasn't been much activity lately and the patch still needs rebase. What is the status here?\n\n* Is it still relevant? âž¡ï¸ Please solve the conflicts to make it ready for review and to ensure the CI passes.\n* Is it no longer relevant? âž¡ï¸ Please close.\n* Did the author lose interest or time to work on this? âž¡ï¸ Please close it and mark it 'Up for grabs' with the label, so that it can be picked up in the future.\n",
      "user": {
        "login": "DrahtBot",
        "id": 39886733,
        "node_id": "MDQ6VXNlcjM5ODg2NzMz",
        "avatar_url": "https://avatars.githubusercontent.com/u/39886733?v=4",
        "gravatar_id": "",
        "url": "https://api.github.com/users/DrahtBot",
        "html_url": "https://github.com/DrahtBot",
        "followers_url": "https://api.github.com/users/DrahtBot/followers",
        "following_url": "https://api.github.com/users/DrahtBot/following%7B/other_user%7D",
        "gists_url": "https://api.github.com/users/DrahtBot/gists%7B/gist_id%7D",
        "starred_url": "https://api.github.com/users/DrahtBot/starred%7B/owner%7D%7B/repo%7D",
        "subscriptions_url": "https://api.github.com/users/DrahtBot/subscriptions",
        "organizations_url": "https://api.github.com/users/DrahtBot/orgs",
        "repos_url": "https://api.github.com/users/DrahtBot/repos",
        "events_url": "https://api.github.com/users/DrahtBot/events%7B/privacy%7D",
        "received_events_url": "https://api.github.com/users/DrahtBot/received_events",
        "type": "User",
        "site_admin": false
      },
      "html_url": "https://github.com/bitcoin/bitcoin/pull/26573#issuecomment-1562129950",
      "issue_url": "https://api.github.com/repos/bitcoin/bitcoin/issues/26573"
    }
  ],
  "comments": []
}